Workbook

Sheet Bai tap chinh
A1: Unit | B1: Revenue | C1: State | D1: Name | E1: Standard name | F1: ID | G1: Start | H1: End | I1: Grading | J1: Intro | K1: Num_days | L1: Month | M1: Income | N1: expected income | P1: Unit | Q1: num_employees | S1: R_sum | T1: R_average | V1: Doanh thu | W1: Xếp loại | X1: Colour
A2: Sales | B2: 5950 | C2: Hoàn thành | D2: HOANG VAN E | E2: =PROPER(D2) -> Hoang Van E | F2: =LEFT(D2,1) & MID(D2,FIND(" ",D2)+1, 1) & RIGHT(D2, 1) & "_" & UPPER(LEFT(A2,3)) & "_" & COUNTIFS(D$2:D2,D2,A$2:A2,A2) -> HVE_SAL_1 | G2: 45460 | H2: 45467 | I2: {=_xlfn.IFS(B2>8000, "Xuất sắc", B2>=5000, "Đạt", B2<5000, "Cần cải thiện")} -> Đạt | J2: =PROPER(D2) & " thuộc bộ phận " & A2 -> Hoang Van E thuộc bộ phận Sales | K2: =H2-G2 -> 7 | L2: =TEXT(H2, "mmmm") -> June | M2: =VLOOKUP(A2, 'Bang luong tra cuu'!$A$2:$B$5, 2, FALSE) -> 6000 | N2: {=M2+B2*_xlfn.IFS(I2="Xuất sắc",20%, I2="Đạt",10%, I2="Cần cải thiện", 5%)} -> 6595 | P2: Toàn bộ | Q2: =COUNTA(A2:A31) -> 30 | S2: =SUMIF(C2:C31, "Hoàn thành", B2:B31) -> 100476 | V2: > 8000 | W2: Xuất sắc | X2: Xanh lá
A3: HR | B3: 4239 | C3: Chưa hoàn | D3: DANG THI F | E3: =PROPER(D3) -> Dang Thi F | F3: =LEFT(D3,1) & MID(D3,FIND(" ",D3)+1, 1) & RIGHT(D3, 1) & "_" & UPPER(LEFT(A3,3)) & "_" & COUNTIFS(D$2:D3,D3,A$2:A3,A3) -> DTF_HR_1 | G3: 45448 | H3: 45456 | I3: {=_xlfn.IFS(B3>8000, "Xuất sắc", B3>=5000, "Đạt", B3<5000, "Cần cải thiện")} -> Cần cải thiện | J3: =PROPER(D3) & " thuộc bộ phận " & A3 -> Dang Thi F thuộc bộ phận HR | K3: =H3-G3 -> 8 | L3: =TEXT(H3, "mmmm") -> June | M3: =VLOOKUP(A3, 'Bang luong tra cuu'!$A$2:$B$5, 2, FALSE) -> 4000 | N3: {=M3+B3*_xlfn.IFS(I3="Xuất sắc",20%, I3="Đạt",10%, I3="Cần cải thiện", 5%)} -> 4211.95 | P3: Sales | Q3: =COUNTIF(A2:A31, "Sales") -> 7 | S3: =SUMIFS(B2:B31, A2:A31, "Sales", C2:C31, "Hoàn thành") -> 27008 | T3: =AVERAGEIF(A2:A31, "Sales", B2:B31) -> 5357.4286 | V3: từ 5000-8000 | W3: Đạt | X3: Xanh dương
A4: HR | B4: 8269 | C4: Chưa hoàn | D4: TRINH VAN I | E4: =PROPER(D4) -> Trinh Van I | F4: =LEFT(D4,1) & MID(D4,FIND(" ",D4)+1, 1) & RIGHT(D4, 1) & "_" & UPPER(LEFT(A4,3)) & "_" & COUNTIFS(D$2:D4,D4,A$2:A4,A4) -> TVI_HR_1 | G4: 45457 | H4: 45463 | I4: {=_xlfn.IFS(B4>8000, "Xuất sắc", B4>=5000, "Đạt", B4<5000, "Cần cải thiện")} -> Xuất sắc | J4: =PROPER(D4) & " thuộc bộ phận " & A4 -> Trinh Van I thuộc bộ phận HR | K4: =H4-G4 -> 6 | L4: =TEXT(H4, "mmmm") -> June | M4: =VLOOKUP(A4, 'Bang luong tra cuu'!$A$2:$B$5, 2, FALSE) -> 4000 | N4: {=M4+B4*_xlfn.IFS(I4="Xuất sắc",20%, I4="Đạt",10%, I4="Cần cải thiện", 5%)} -> 5653.8 | P4: HR | Q4: =COUNTIF(A2:A31, "HR") -> 7 | S4: =SUMIFS(B2:B31, A2:A31, "HR", C2:C31, "Hoàn thành") -> 15183 | T4: =AVERAGEIF(A2:A31, "HR", B2:B31) -> 5866 | V4: <5000 | W4: Cần cải thiện | X4: Đỏ
A5: IT | B5: 6350 | C5: Chưa hoàn | D5: NGUYEN VAN A | E5: =PROPER(D5) -> Nguyen Van A | F5: =LEFT(D5,1) & MID(D5,FIND(" ",D5)+1, 1) & RIGHT(D5, 1) & "_" & UPPER(LEFT(A5,3)) & "_" & COUNTIFS(D$2:D5,D5,A$2:A5,A5) -> NVA_IT_1 | G5: 45454 | H5: 45459 | I5: {=_xlfn.IFS(B5>8000, "Xuất sắc", B5>=5000, "Đạt", B5<5000, "Cần cải thiện")} -> Đạt | J5: =PROPER(D5) & " thuộc bộ phận " & A5 -> Nguyen Van A thuộc bộ phận IT | K5: =H5-G5 -> 5 | L5: =TEXT(H5, "mmmm") -> June | M5: =VLOOKUP(A5, 'Bang luong tra cuu'!$A$2:$B$5, 2, FALSE) -> 6500 | N5: {=M5+B5*_xlfn.IFS(I5="Xuất sắc",20%, I5="Đạt",10%, I5="Cần cải thiện", 5%)} -> 7135 | P5: IT | Q5: =COUNTIF(A2:A31, "IT") -> 7 | S5: =SUMIFS(B2:B31, A2:A31, "IT", C2:C31, "Hoàn thành") -> 7824 | T5: =AVERAGEIF(A2:A31, "IT", B2:B31) -> 5138.7143
A6: Marketing | B6: 4741 | C6: Hoàn thành | D6: BUI VAN G | E6: =PROPER(D6) -> Bui Van G | F6: =LEFT(D6,1) & MID(D6,FIND(" ",D6)+1, 1) & RIGHT(D6, 1) & "_" & UPPER(LEFT(A6,3)) & "_" & COUNTIFS(D$2:D6,D6,A$2:A6,A6) -> BVG_MAR_1 | G6: 45458 | H6: 45463 | I6: {=_xlfn.IFS(B6>8000, "Xuất sắc", B6>=5000, "Đạt", B6<5000, "Cần cải thiện")} -> Cần cải thiện | J6: =PROPER(D6) & " thuộc bộ phận " & A6 -> Bui Van G thuộc bộ phận Marketing | K6: =H6-G6 -> 5 | L6: =TEXT(H6, "mmmm") -> June | M6: =VLOOKUP(A6, 'Bang luong tra cuu'!$A$2:$B$5, 2, FALSE) -> 5500 | N6: {=M6+B6*_xlfn.IFS(I6="Xuất sắc",20%, I6="Đạt",10%, I6="Cần cải thiện", 5%)} -> 5737.05 | P6: Marketing | Q6: =COUNTIF(A2:A31, "Marketing") -> 9 | S6: =SUMIFS(B2:B31, A2:A31, "Marketing", C2:C31, "Hoàn thành") -> 50461 | T6: =AVERAGEIF(A2:A31, "Marketing", B2:B31) -> 6173.6667
A7: HR | B7: 8123 | C7: Chưa hoàn | D7: PHAM THI D | E7: =PROPER(D7) -> Pham Thi D | F7: =LEFT(D7,1) & MID(D7,FIND(" ",D7)+1, 1) & RIGHT(D7, 1) & "_" & UPPER(LEFT(A7,3)) & "_" & COUNTIFS(D$2:D7,D7,A$2:A7,A7) -> PTD_HR_1 | G7: 45457 | H7: 45466 | I7: {=_xlfn.IFS(B7>8000, "Xuất sắc", B7>=5000, "Đạt", B7<5000, "Cần cải thiện")} -> Xuất sắc | J7: =PROPER(D7) & " thuộc bộ phận " & A7 -> Pham Thi D thuộc bộ phận HR | K7: =H7-G7 -> 9 | L7: =TEXT(H7, "mmmm") -> June | M7: =VLOOKUP(A7, 'Bang luong tra cuu'!$A$2:$B$5, 2, FALSE) -> 4000 | N7: {=M7+B7*_xlfn.IFS(I7="Xuất sắc",20%, I7="Đạt",10%, I7="Cần cải thiện", 5%)} -> 5624.6
A8: IT | B8: 7700 | C8: Chưa hoàn | D8: DO THI H | E8: =PROPER(D8) -> Do Thi H | F8: =LEFT(D8,1) & MID(D8,FIND(" ",D8)+1, 1) & RIGHT(D8, 1) & "_" & UPPER(LEFT(A8,3)) & "_" & COUNTIFS(D$2:D8,D8,A$2:A8,A8) -> DTH_IT_1 | G8: 45446 | H8: 45455 | I8: {=_xlfn.IFS(B8>8000, "Xuất sắc", B8>=5000, "Đạt", B8<5000, "Cần cải thiện")} -> Đạt | J8: =PROPER(D8) & " thuộc bộ phận " & A8 -> Do Thi H thuộc bộ phận IT | K8: =H8-G8 -> 9 | L8: =TEXT(H8, "mmmm") -> June | M8: =VLOOKUP(A8, 'Bang luong tra cuu'!$A$2:$B$5, 2, FALSE) -> 6500 | N8: {=M8+B8*_xlfn.IFS(I8="Xuất sắc",20%, I8="Đạt",10%, I8="Cần cải thiện", 5%)} -> 7270 | P8: =COUNTIF(L2:L31, "June") -> 28
A9: Marketing | B9: 2927 | C9: Hoàn thành | D9: DO THI H | E9: =PROPER(D9) -> Do Thi H | F9: =LEFT(D9,1) & MID(D9,FIND(" ",D9)+1, 1) & RIGHT(D9, 1) & "_" & UPPER(LEFT(A9,3)) & "_" & COUNTIFS(D$2:D9,D9,A$2:A9,A9) -> DTH_MAR_1 | G9: 45461 | H9: 45464 | I9: {=_xlfn.IFS(B9>8000, "Xuất sắc", B9>=5000, "Đạt", B9<5000, "Cần cải thiện")} -> Cần cải thiện | J9: =PROPER(D9) & " thuộc bộ phận " & A9 -> Do Thi H thuộc bộ phận Marketing | K9: =H9-G9 -> 3 | L9: =TEXT(H9, "mmmm") -> June | M9: =VLOOKUP(A9, 'Bang luong tra cuu'!$A$2:$B$5, 2, FALSE) -> 5500 | N9: {=M9+B9*_xlfn.IFS(I9="Xuất sắc",20%, I9="Đạt",10%, I9="Cần cải thiện", 5%)} -> 5646.35 | P9: =COUNTIF(L2:L31, "July") -> 2
A10: IT | B10: 4925 | C10: Hoàn thành | D10: PHAM THI D | E10: =PROPER(D10) -> Pham Thi D | F10: =LEFT(D10,1) & MID(D10,FIND(" ",D10)+1, 1) & RIGHT(D10, 1) & "_" & UPPER(LEFT(A10,3)) & "_" & COUNTIFS(D$2:D10,D10,A$2:A10,A10) -> PTD_IT_1 | G10: 45459 | H10: 45462 | I10: {=_xlfn.IFS(B10>8000, "Xuất sắc", B10>=5000, "Đạt", B10<5000, "Cần cải thiện")} -> Cần cải thiện | J10: =PROPER(D10) & " thuộc bộ phận " & A10 -> Pham Thi D thuộc bộ phận IT | K10: =H10-G10 -> 3 | L10: =TEXT(H10, "mmmm") -> June | M10: =VLOOKUP(A10, 'Bang luong tra cuu'!$A$2:$B$5, 2, FALSE) -> 6500 | N10: {=M10+B10*_xlfn.IFS(I10="Xuất sắc",20%, I10="Đạt",10%, I10="Cần cải thiện", 5%)} -> 6746.25
A11: HR | B11: 8783 | C11: Hoàn thành | D11: HOANG VAN E | E11: =PROPER(D11) -> Hoang Van E | F11: =LEFT(D11,1) & MID(D11,FIND(" ",D11)+1, 1) & RIGHT(D11, 1) & "_" & UPPER(LEFT(A11,3)) & "_" & COUNTIFS(D$2:D11,D11,A$2:A11,A11) -> HVE_HR_1 | G11: 45446 | H11: 45453 | I11: {=_xlfn.IFS(B11>8000, "Xuất sắc", B11>=5000, "Đạt", B11<5000, "Cần cải thiện")} -> Xuất sắc | J11: =PROPER(D11) & " thuộc bộ phận " & A11 -> Hoang Van E thuộc bộ phận HR | K11: =H11-G11 -> 7 | L11: =TEXT(H11, "mmmm") -> June | M11: =VLOOKUP(A11, 'Bang luong tra cuu'!$A$2:$B$5, 2, FALSE) -> 4000 | N11: {=M11+B11*_xlfn.IFS(I11="Xuất sắc",20%, I11="Đạt",10%, I11="Cần cải thiện", 5%)} -> 5756.6 | P11: Grading | Q11: % thưởng theo doanh thu
A12: Sales | B12: 7544 | C12: Chưa hoàn | D12: DANG THI F | E12: =PROPER(D12) -> Dang Thi F | F12: =LEFT(D12,1) & MID(D12,FIND(" ",D12)+1, 1) & RIGHT(D12, 1) & "_" & UPPER(LEFT(A12,3)) & "_" & COUNTIFS(D$2:D12,D12,A$2:A12,A12) -> DTF_SAL_1 | G12: 45447 | H12: 45453 | I12: {=_xlfn.IFS(B12>8000, "Xuất sắc", B12>=5000, "Đạt", B12<5000, "Cần cải thiện")} -> Đạt | J12: =PROPER(D12) & " thuộc bộ phận " & A12 -> Dang Thi F thuộc bộ phận Sales | K12: =H12-G12 -> 6 | L12: =TEXT(H12, "mmmm") -> June | M12: =VLOOKUP(A12, 'Bang luong tra cuu'!$A$2:$B$5, 2, FALSE) -> 6000 | N12: {=M12+B12*_xlfn.IFS(I12="Xuất sắc",20%, I12="Đạt",10%, I12="Cần cải thiện", 5%)} -> 6754.4 | P12: Xuất sắc | Q12: 0.2
A13: Sales | B13: 4811 | C13: Hoàn thành | D13: LE VAN C | E13: =PROPER(D13) -> Le Van C | F13: =LEFT(D13,1) & MID(D13,FIND(" ",D13)+1, 1) & RIGHT(D13, 1) & "_" & UPPER(LEFT(A13,3)) & "_" & COUNTIFS(D$2:D13,D13,A$2:A13,A13) -> LVC_SAL_1 | G13: 45453 | H13: 45461 | I13: {=_xlfn.IFS(B13>8000, "Xuất sắc", B13>=5000, "Đạt", B13<5000, "Cần cải thiện")} -> Cần cải thiện | J13: =PROPER(D13) & " thuộc bộ phận " & A13 -> Le Van C thuộc bộ phận Sales | K13: =H13-G13 -> 8 | L13: =TEXT(H13, "mmmm") -> June | M13: =VLOOKUP(A13, 'Bang luong tra cuu'!$A$2:$B$5, 2, FALSE) -> 6000 | N13: {=M13+B13*_xlfn.IFS(I13="Xuất sắc",20%, I13="Đạt",10%, I13="Cần cải thiện", 5%)} -> 6240.55 | P13: Đạt | Q13: 0.1
A14: IT | B14: 5680 | C14: Chưa hoàn | D14: PHAM THI D | E14: =PROPER(D14) -> Pham Thi D | F14: =LEFT(D14,1) & MID(D14,FIND(" ",D14)+1, 1) & RIGHT(D14, 1) & "_" & UPPER(LEFT(A14,3)) & "_" & COUNTIFS(D$2:D14,D14,A$2:A14,A14) -> PTD_IT_2 | G14: 45458 | H14: 45463 | I14: {=_xlfn.IFS(B14>8000, "Xuất sắc", B14>=5000, "Đạt", B14<5000, "Cần cải thiện")} -> Đạt | J14: =PROPER(D14) & " thuộc bộ phận " & A14 -> Pham Thi D thuộc bộ phận IT | K14: =H14-G14 -> 5 | L14: =TEXT(H14, "mmmm") -> June | M14: =VLOOKUP(A14, 'Bang luong tra cuu'!$A$2:$B$5, 2, FALSE) -> 6500 | N14: {=M14+B14*_xlfn.IFS(I14="Xuất sắc",20%, I14="Đạt",10%, I14="Cần cải thiện", 5%)} -> 7068 | P14: Cần cải thiện | Q14: 0.05
A15: Marketing | B15: 9965 | C15: Hoàn thành | D15: NGUYEN VAN A | E15: =PROPER(D15) -> Nguyen Van A | F15: =LEFT(D15,1) & MID(D15,FIND(" ",D15)+1, 1) & RIGHT(D15, 1) & "_" & UPPER(LEFT(A15,3)) & "_" & COUNTIFS(D$2:D15,D15,A$2:A15,A15) -> NVA_MAR_1 | G15: 45449 | H15: 45481 | I15: {=_xlfn.IFS(B15>8000, "Xuất sắc", B15>=5000, "Đạt", B15<5000, "Cần cải thiện")} -> Xuất sắc | J15: =PROPER(D15) & " thuộc bộ phận " & A15 -> Nguyen Van A thuộc bộ phận Marketing | K15: =H15-G15 -> 32 | L15: =TEXT(H15, "mmmm") -> July | M15: =VLOOKUP(A15, 'Bang luong tra cuu'!$A$2:$B$5, 2, FALSE) -> 5500 | N15: {=M15+B15*_xlfn.IFS(I15="Xuất sắc",20%, I15="Đạt",10%, I15="Cần cải thiện", 5%)} -> 7493
A16: HR | B16: 5248 | C16: Chưa hoàn | D16: DANG THI F | E16: =PROPER(D16) -> Dang Thi F | F16: =LEFT(D16,1) & MID(D16,FIND(" ",D16)+1, 1) & RIGHT(D16, 1) & "_" & UPPER(LEFT(A16,3)) & "_" & COUNTIFS(D$2:D16,D16,A$2:A16,A16) -> DTF_HR_2 | G16: 45462 | H16: 45464 | I16: {=_xlfn.IFS(B16>8000, "Xuất sắc", B16>=5000, "Đạt", B16<5000, "Cần cải thiện")} -> Đạt | J16: =PROPER(D16) & " thuộc bộ phận " & A16 -> Dang Thi F thuộc bộ phận HR | K16: =H16-G16 -> 2 | L16: =TEXT(H16, "mmmm") -> June | M16: =VLOOKUP(A16, 'Bang luong tra cuu'!$A$2:$B$5, 2, FALSE) -> 4000 | N16: {=M16+B16*_xlfn.IFS(I16="Xuất sắc",20%, I16="Đạt",10%, I16="Cần cải thiện", 5%)} -> 4524.8
A17: Marketing | B17: 5062 | C17: Hoàn thành | D17: NGUYEN VAN A | E17: =PROPER(D17) -> Nguyen Van A | F17: =LEFT(D17,1) & MID(D17,FIND(" ",D17)+1, 1) & RIGHT(D17, 1) & "_" & UPPER(LEFT(A17,3)) & "_" & COUNTIFS(D$2:D17,D17,A$2:A17,A17) -> NVA_MAR_2 | G17: 45453 | H17: 45456 | I17: {=_xlfn.IFS(B17>8000, "Xuất sắc", B17>=5000, "Đạt", B17<5000, "Cần cải thiện")} -> Đạt | J17: =PROPER(D17) & " thuộc bộ phận " & A17 -> Nguyen Van A thuộc bộ phận Marketing | K17: =H17-G17 -> 3 | L17: =TEXT(H17, "mmmm") -> June | M17: =VLOOKUP(A17, 'Bang luong tra cuu'!$A$2:$B$5, 2, FALSE) -> 5500 | N17: {=M17+B17*_xlfn.IFS(I17="Xuất sắc",20%, I17="Đạt",10%, I17="Cần cải thiện", 5%)} -> 6006.2
A18: Sales | B18: 2950 | C18: Chưa hoàn | D18: TRAN THI B | E18: =PROPER(D18) -> Tran Thi B | F18: =LEFT(D18,1) & MID(D18,FIND(" ",D18)+1, 1) & RIGHT(D18, 1) & "_" & UPPER(LEFT(A18,3)) & "_" & COUNTIFS(D$2:D18,D18,A$2:A18,A18) -> TTB_SAL_1 | G18: 45462 | H18: 45470 | I18: {=_xlfn.IFS(B18>8000, "Xuất sắc", B18>=5000, "Đạt", B18<5000, "Cần cải thiện")} -> Cần cải thiện | J18: =PROPER(D18) & " thuộc bộ phận " & A18 -> Tran Thi B thuộc bộ phận Sales | K18: =H18-G18 -> 8 | L18: =TEXT(H18, "mmmm") -> June | M18: =VLOOKUP(A18, 'Bang luong tra cuu'!$A$2:$B$5, 2, FALSE) -> 6000 | N18: {=M18+B18*_xlfn.IFS(I18="Xuất sắc",20%, I18="Đạt",10%, I18="Cần cải thiện", 5%)} -> 6147.5
A19: IT | B19: 2899 | C19: Hoàn thành | D19: NGUYEN THI J | E19: =PROPER(D19) -> Nguyen Thi J | F19: =LEFT(D19,1) & MID(D19,FIND(" ",D19)+1, 1) & RIGHT(D19, 1) & "_" & UPPER(LEFT(A19,3)) & "_" & COUNTIFS(D$2:D19,D19,A$2:A19,A19) -> NTJ_IT_1 | G19: 45446 | H19: 45450 | I19: {=_xlfn.IFS(B19>8000, "Xuất sắc", B19>=5000, "Đạt", B19<5000, "Cần cải thiện")} -> Cần cải thiện | J19: =PROPER(D19) & " thuộc bộ phận " & A19 -> Nguyen Thi J thuộc bộ phận IT | K19: =H19-G19 -> 4 | L19: =TEXT(H19, "mmmm") -> June | M19: =VLOOKUP(A19, 'Bang luong tra cuu'!$A$2:$B$5, 2, FALSE) -> 6500 | N19: {=M19+B19*_xlfn.IFS(I19="Xuất sắc",20%, I19="Đạt",10%, I19="Cần cải thiện", 5%)} -> 6644.95
A20: IT | B20: 5771 | C20: Chưa hoàn | D20: HOANG VAN E | E20: =PROPER(D20) -> Hoang Van E | F20: =LEFT(D20,1) & MID(D20,FIND(" ",D20)+1, 1) & RIGHT(D20, 1) & "_" & UPPER(LEFT(A20,3)) & "_" & COUNTIFS(D$2:D20,D20,A$2:A20,A20) -> HVE_IT_1 | G20: 45457 | H20: 45463 | I20: {=_xlfn.IFS(B20>8000, "Xuất sắc", B20>=5000, "Đạt", B20<5000, "Cần cải thiện")} -> Đạt | J20: =PROPER(D20) & " thuộc bộ phận " & A20 -> Hoang Van E thuộc bộ phận IT | K20: =H20-G20 -> 6 | L20: =TEXT(H20, "mmmm") -> June | M20: =VLOOKUP(A20, 'Bang luong tra cuu'!$A$2:$B$5, 2, FALSE) -> 6500 | N20: {=M20+B20*_xlfn.IFS(I20="Xuất sắc",20%, I20="Đạt",10%, I20="Cần cải thiện", 5%)} -> 7077.1
A21: IT | B21: 2646 | C21: Chưa hoàn | D21: NGUYEN VAN A | E21: =PROPER(D21) -> Nguyen Van A | F21: =LEFT(D21,1) & MID(D21,FIND(" ",D21)+1, 1) & RIGHT(D21, 1) & "_" & UPPER(LEFT(A21,3)) & "_" & COUNTIFS(D$2:D21,D21,A$2:A21,A21) -> NVA_IT_2 | G21: 45456 | H21: 45459 | I21: {=_xlfn.IFS(B21>8000, "Xuất sắc", B21>=5000, "Đạt", B21<5000, "Cần cải thiện")} -> Cần cải thiện | J21: =PROPER(D21) & " thuộc bộ phận " & A21 -> Nguyen Van A thuộc bộ phận IT | K21: =H21-G21 -> 3 | L21: =TEXT(H21, "mmmm") -> June | M21: =VLOOKUP(A21, 'Bang luong tra cuu'!$A$2:$B$5, 2, FALSE) -> 6500 | N21: {=M21+B21*_xlfn.IFS(I21="Xuất sắc",20%, I21="Đạt",10%, I21="Cần cải thiện", 5%)} -> 6632.3
A22: Marketing | B22: 8864 | C22: Hoàn thành | D22: PHAM THI D | E22: =PROPER(D22) -> Pham Thi D | F22: =LEFT(D22,1) & MID(D22,FIND(" ",D22)+1, 1) & RIGHT(D22, 1) & "_" & UPPER(LEFT(A22,3)) & "_" & COUNTIFS(D$2:D22,D22,A$2:A22,A22) -> PTD_MAR_1 | G22: 45445 | H22: 45454 | I22: {=_xlfn.IFS(B22>8000, "Xuất sắc", B22>=5000, "Đạt", B22<5000, "Cần cải thiện")} -> Xuất sắc | J22: =PROPER(D22) & " thuộc bộ phận " & A22 -> Pham Thi D thuộc bộ phận Marketing | K22: =H22-G22 -> 9 | L22: =TEXT(H22, "mmmm") -> June | M22: =VLOOKUP(A22, 'Bang luong tra cuu'!$A$2:$B$5, 2, FALSE) -> 5500 | N22: {=M22+B22*_xlfn.IFS(I22="Xuất sắc",20%, I22="Đạt",10%, I22="Cần cải thiện", 5%)} -> 7272.8
A23: Marketing | B23: 8659 | C23: Hoàn thành | D23: BUI VAN G | E23: =PROPER(D23) -> Bui Van G | F23: =LEFT(D23,1) & MID(D23,FIND(" ",D23)+1, 1) & RIGHT(D23, 1) & "_" & UPPER(LEFT(A23,3)) & "_" & COUNTIFS(D$2:D23,D23,A$2:A23,A23) -> BVG_MAR_2 | G23: 45457 | H23: 45459 | I23: {=_xlfn.IFS(B23>8000, "Xuất sắc", B23>=5000, "Đạt", B23<5000, "Cần cải thiện")} -> Xuất sắc | J23: =PROPER(D23) & " thuộc bộ phận " & A23 -> Bui Van G thuộc bộ phận Marketing | K23: =H23-G23 -> 2 | L23: =TEXT(H23, "mmmm") -> June | M23: =VLOOKUP(A23, 'Bang luong tra cuu'!$A$2:$B$5, 2, FALSE) -> 5500 | N23: {=M23+B23*_xlfn.IFS(I23="Xuất sắc",20%, I23="Đạt",10%, I23="Cần cải thiện", 5%)} -> 7231.8
A24: Sales | B24: 2125 | C24: Hoàn thành | D24: TRAN THI B | E24: =PROPER(D24) -> Tran Thi B | F24: =LEFT(D24,1) & MID(D24,FIND(" ",D24)+1, 1) & RIGHT(D24, 1) & "_" & UPPER(LEFT(A24,3)) & "_" & COUNTIFS(D$2:D24,D24,A$2:A24,A24) -> TTB_SAL_2 | G24: 45444 | H24: 45450 | I24: {=_xlfn.IFS(B24>8000, "Xuất sắc", B24>=5000, "Đạt", B24<5000, "Cần cải thiện")} -> Cần cải thiện | J24: =PROPER(D24) & " thuộc bộ phận " & A24 -> Tran Thi B thuộc bộ phận Sales | K24: =H24-G24 -> 6 | L24: =TEXT(H24, "mmmm") -> June | M24: =VLOOKUP(A24, 'Bang luong tra cuu'!$A$2:$B$5, 2, FALSE) -> 6000 | N24: {=M24+B24*_xlfn.IFS(I24="Xuất sắc",20%, I24="Đạt",10%, I24="Cần cải thiện", 5%)} -> 6106.25
A25: HR | B25: 4323 | C25: Hoàn thành | D25: NGUYEN THI J | E25: =PROPER(D25) -> Nguyen Thi J | F25: =LEFT(D25,1) & MID(D25,FIND(" ",D25)+1, 1) & RIGHT(D25, 1) & "_" & UPPER(LEFT(A25,3)) & "_" & COUNTIFS(D$2:D25,D25,A$2:A25,A25) -> NTJ_HR_1 | G25: 45453 | H25: 45457 | I25: {=_xlfn.IFS(B25>8000, "Xuất sắc", B25>=5000, "Đạt", B25<5000, "Cần cải thiện")} -> Cần cải thiện | J25: =PROPER(D25) & " thuộc bộ phận " & A25 -> Nguyen Thi J thuộc bộ phận HR | K25: =H25-G25 -> 4 | L25: =TEXT(H25, "mmmm") -> June | M25: =VLOOKUP(A25, 'Bang luong tra cuu'!$A$2:$B$5, 2, FALSE) -> 4000 | N25: {=M25+B25*_xlfn.IFS(I25="Xuất sắc",20%, I25="Đạt",10%, I25="Cần cải thiện", 5%)} -> 4216.15
A26: Sales | B26: 7969 | C26: Hoàn thành | D26: TRINH VAN I | E26: =PROPER(D26) -> Trinh Van I | F26: =LEFT(D26,1) & MID(D26,FIND(" ",D26)+1, 1) & RIGHT(D26, 1) & "_" & UPPER(LEFT(A26,3)) & "_" & COUNTIFS(D$2:D26,D26,A$2:A26,A26) -> TVI_SAL_1 | G26: 45458 | H26: 45460 | I26: {=_xlfn.IFS(B26>8000, "Xuất sắc", B26>=5000, "Đạt", B26<5000, "Cần cải thiện")} -> Đạt | J26: =PROPER(D26) & " thuộc bộ phận " & A26 -> Trinh Van I thuộc bộ phận Sales | K26: =H26-G26 -> 2 | L26: =TEXT(H26, "mmmm") -> June | M26: =VLOOKUP(A26, 'Bang luong tra cuu'!$A$2:$B$5, 2, FALSE) -> 6000 | N26: {=M26+B26*_xlfn.IFS(I26="Xuất sắc",20%, I26="Đạt",10%, I26="Cần cải thiện", 5%)} -> 6796.9
... A31: Marketing | B31: 5102 | C31: Chưa hoàn | D31: DANG THI F | E31: =PROPER(D31) -> Dang Thi F | F31: =LEFT(D31,1) & MID(D31,FIND(" ",D31)+1, 1) & RIGHT(D31, 1) & "_" & UPPER(LEFT(A31,3)) & "_" & COUNTIFS(D$2:D31,D31,A$2:A31,A31) -> DTF_MAR_2 | G31: 45450 | H31: 45485 | I31: {=_xlfn.IFS(B31>8000, "Xuất sắc", B31>=5000, "Đạt", B31<5000, "Cần cải thiện")} -> Đạt | J31: =PROPER(D31) & " thuộc bộ phận " & A31 -> Dang Thi F thuộc bộ phận Marketing | K31: =H31-G31 -> 35 | L31: =TEXT(H31, "mmmm") -> July | M31: =VLOOKUP(A31, 'Bang luong tra cuu'!$A$2:$B$5, 2, FALSE) -> 5500 | N31: {=M31+B31*_xlfn.IFS(I31="Xuất sắc",20%, I31="Đạt",10%, I31="Cần cải thiện", 5%)} -> 6010.2

Sheet Bang luong tra cuu
A1: Bộ phận | B1: Lương cơ bản
A2: Sales | B2: 6000
A3: HR | B3: 4000
A4: Marketing | B4: 5500
A5: IT | B5: 6500
